morse_python/__init__.py
morse_python/morse.py
morse_python-1.1.dist-info/licenses/LICENSE
morse_python-1.1.dist-info/METADATA
morse_python-1.1.dist-info/WHEEL
morse_python-1.1.dist-info/top_level.txt
morse_python-1.1.dist-info/RECORD
