Metadata-Version: 2.4
Name: morse_python
Version: 1.1
Summary: Library for coding in Python with morse code
Home-page: https://github.com/ame-tisto/morse_python
Author: Mattia Capuano AKA: Ametisto
Author-email: mattia.capuano1508@gmail.com
Classifier: Programming Language :: Python :: 3
Classifier: License :: OSI Approved :: MIT License
Classifier: Operating System :: OS Independent
Requires-Python: >=3.7
License-File: LICENSE
Requires-Dist: pygame
Requires-Dist: numpy
Dynamic: author
Dynamic: author-email
Dynamic: classifier
Dynamic: description
Dynamic: description-content-type
Dynamic: home-page
Dynamic: license-file
Dynamic: requires-dist
Dynamic: requires-python
Dynamic: summary
